MANIFEST.in
setup.cfg
setup.py
versioneer.py
rcgrep/__init__.py
rcgrep/_version.py
rcgrep/cli.py
rcgrep/search.py
rcgrep.egg-info/PKG-INFO
rcgrep.egg-info/SOURCES.txt
rcgrep.egg-info/dependency_links.txt
rcgrep.egg-info/entry_points.txt
rcgrep.egg-info/top_level.txt
rcgrep.egg-info/zip-safe
rcgrep/tests/__init__.py
rcgrep/tests/test_cli.py
rcgrep/tests/test_search.py
rcgrep/tests/test_utils.py
rcgrep/tests/data/mrj.gdna.fa
rcgrep/tests/data/pbar.fa.gz
rcgrep/tests/data/reads.fq.bz2